docs/Makefile
docs/plots_how_to_use/LIMRAD_time_spectrogram.png
docs/plots_how_to_use/MIRA_Z.png
docs/plots_how_to_use/MIRA_ppi_scan_vel.png
docs/plots_how_to_use/MIRA_range_spectrogram.png
docs/plots_how_to_use/MIRA_rhi_scan_SLDR.png
docs/plots_how_to_use/POLLYNET_quasi_bsc_with_inset.png
docs/plots_how_to_use/cloudnet_Z.png
docs/plots_how_to_use/cloudnet_class.png
docs/plots_how_to_use/hatpro_iwv_resampled.png
docs/plots_how_to_use/horizontal_wind_barbs.png
docs/plots_how_to_use/limrad_FOC_example.png
docs/plots_how_to_use/parsivel_rain_rate.png
docs/plots_how_to_use/polly_bsc1064.png
docs/plots_how_to_use/radar-lwp_hatpro-rainflag.png
docs/plots_how_to_use/scatter_mira_limrad_Z.png
docs/plots_how_to_use/scatter_mira_limrad_Z_by_VEL.png
docs/plots_how_to_use/single_spec.png
docs/source/README.md
docs/source/api_overview.rst
docs/source/conf.py
docs/source/contributors.rst
docs/source/datacontainer_and_transformation.rst
docs/source/guide_config.rst
docs/source/how_to_use.rst
docs/source/index.rst
docs/source/package.rst
docs/source/peakTree.rst
docs/source/setup_remote.rst
docs/source/spectra.rst
docs/source/examples/LIMRAD94_to_Cloudnet_v2.py
docs/source/examples/api.png
docs/source/examples/direct_filepaths.py
docs/source/examples/download_plot_sounding.py
docs/source/examples/example_description.py
docs/source/examples/freq_of_occurrence.py
docs/source/examples/interpolate_example_pL3.py
docs/source/examples/plot_daily_remote.py
docs/source/examples/plot_overlay.py
docs/source/examples/scan_example.py
docs/source/examples/scatter_Z_mdv.py
docs/source/examples/scatter_and_dwr.py
docs/source/examples/scatter_velocity.py
docs/source/examples/simple_example_pL3.py
docs/source/examples/spec_example_pL3.py
examples/LIMRAD94_to_Cloudnet_v2.py
examples/api.png
examples/direct_filepaths.py
examples/download_plot_sounding.py
examples/example_description.py
examples/freq_of_occurrence.py
examples/interpolate_example_pL3.py
examples/plot_daily_remote.py
pylarda-3.3.11.dist-info/licenses/LICENSE
pylarda-3.3.11.dist-info/METADATA
pylarda-3.3.11.dist-info/WHEEL
pylarda-3.3.11.dist-info/top_level.txt
pylarda-3.3.11.dist-info/RECORD
