Metadata-Version: 2.4
Name: pyLARDA
Version: 3.3.11
Summary: Data cube for handling atmospheric observations of profiling remote sensing instruments.
Author: pyLARDA-dev-team
License-Expression: MIT
Project-URL: Homepage, https://github.com/lacros-tropos/larda'
Classifier: Programming Language :: Python :: 3
Classifier: Operating System :: OS Independent
Classifier: Intended Audience :: Science/Research
Classifier: Topic :: Scientific/Engineering
Requires-Python: >=3.8
License-File: LICENSE
Requires-Dist: numpy==2.1
Requires-Dist: scipy
Requires-Dist: netCDF4
Requires-Dist: msgpack
Requires-Dist: xarray
Requires-Dist: matplotlib
Requires-Dist: requests
Requires-Dist: toml
Requires-Dist: tqdm
Requires-Dist: numba
Dynamic: license-file
